pytempura-0.2.0.dist-info/RECORD
pytempura-0.2.0.dist-info/LICENSE
pytempura-0.2.0.dist-info/WHEEL
pytempura-0.2.0.dist-info/METADATA
pytempura/norm_lens.py
pytempura/_libtempura.cpython-312-darwin.so
pytempura/norm.py
pytempura/__init__.py
pytempura/norm_src.py
pytempura/norm_general.py
pytempura/noise_spec.py
pytempura/.dylibs/libgfortran.5.dylib
pytempura/.dylibs/libquadmath.0.dylib
pytempura/.dylibs/libgcc_s.1.1.dylib
pytempura/.dylibs/libgomp.1.dylib
