Metadata-Version: 2.1
Name: pytempura
Version: 0.2.0
Summary: A full-sky quadratic estimator analytic normalization calculator.
Author: Toshiya Namikawa, Mathew Madhavacheril
Maintainer-Email: Toshiya Namikawa <namikawa.toshiya9@gmail.com>, Mathew Madhavacheril <mathewsyriac@gmail.com>
License: 
Requires-Python: >=3.10
Requires-Dist: numpy
Requires-Dist: scipy>=1.0
Requires-Dist: pytest-cov>=2.6
Requires-Dist: coveralls>=1.5
Requires-Dist: pytest>=4.6
Requires-Dist: matplotlib
